{
  "schemaVersion": 1,
  "baseUrl": "https://www.scapestack.org",
  "generatedAt": "2026-07-19T15:58:16.439Z",
  "browser": "149.0.7827.55",
  "runCount": 3,
  "routes": [
    {
      "route": "home",
      "path": "/",
      "viewport": {
        "id": "desktop",
        "width": 1440,
        "height": 1000,
        "isMobile": false
      },
      "cold": [
        {
          "mode": "cold",
          "status": 200,
          "shellReady": true,
          "shellReadyMs": 819,
          "ready": true,
          "navigationError": null,
          "readyError": null,
          "domContentLoadedMs": 769,
          "actionableMs": 819,
          "consoleErrors": [],
          "pageErrors": [],
          "hydrationErrors": [],
          "requestFailures": [],
          "horizontalOverflowPx": 0,
          "brokenImages": [],
          "unnamedControls": [],
          "headings": [
            {
              "level": "h1",
              "text": "Stop bankstanding.Pick the next trip."
            }
          ],
          "axHeadings": [
            "Stop bankstanding. Pick the next trip."
          ],
          "navigationTiming": {
            "responseStartMs": 162,
            "domContentLoadedMs": 767,
            "loadEventMs": 831
          },
          "axArtifact": "docs/qa/outcome-recovery/ODR-01/production/ax/desktop-home.json",
          "screenshotArtifact": "docs/qa/outcome-recovery/ODR-01/production/screenshots/desktop-home.png"
        },
        {
          "mode": "cold",
          "status": 200,
          "shellReady": true,
          "shellReadyMs": 1261,
          "ready": true,
          "navigationError": null,
          "readyError": null,
          "domContentLoadedMs": 1248,
          "actionableMs": 1261,
          "consoleErrors": [],
          "pageErrors": [],
          "hydrationErrors": [],
          "requestFailures": [],
          "horizontalOverflowPx": 0,
          "brokenImages": [],
          "unnamedControls": [],
          "headings": [
            {
              "level": "h1",
              "text": "Stop bankstanding.Pick the next trip."
            }
          ],
          "axHeadings": [
            "Stop bankstanding. Pick the next trip."
          ],
          "navigationTiming": {
            "responseStartMs": 695,
            "domContentLoadedMs": 1247,
            "loadEventMs": 2135
          }
        },
        {
          "mode": "cold",
          "status": 200,
          "shellReady": true,
          "shellReadyMs": 297,
          "ready": true,
          "navigationError": null,
          "readyError": null,
          "domContentLoadedMs": 280,
          "actionableMs": 297,
          "consoleErrors": [],
          "pageErrors": [],
          "hydrationErrors": [],
          "requestFailures": [],
          "horizontalOverflowPx": 0,
          "brokenImages": [],
          "unnamedControls": [],
          "headings": [
            {
              "level": "h1",
              "text": "Stop bankstanding.Pick the next trip."
            }
          ],
          "axHeadings": [
            "Stop bankstanding. Pick the next trip."
          ],
          "navigationTiming": {
            "responseStartMs": 189,
            "domContentLoadedMs": 279,
            "loadEventMs": 428
          }
        }
      ],
      "warm": [
        {
          "mode": "warm",
          "status": 200,
          "shellReady": true,
          "shellReadyMs": 225,
          "ready": true,
          "navigationError": null,
          "readyError": null,
          "domContentLoadedMs": 196,
          "actionableMs": 225,
          "consoleErrors": [],
          "pageErrors": [],
          "hydrationErrors": [],
          "requestFailures": [
            {
              "url": "https://www.scapestack.org/?_rsc=7h4NYy5eoyMcNlUN",
              "method": "GET",
              "error": "net::ERR_ABORTED"
            },
            {
              "url": "https://www.scapestack.org/api/account/me",
              "method": "GET",
              "error": "net::ERR_ABORTED"
            },
            {
              "url": "https://www.scapestack.org/dps?_rsc=U4W3Jn2W64qAyj-2",
              "method": "GET",
              "error": "net::ERR_ABORTED"
            },
            {
              "url": "https://www.scapestack.org/api/account/me",
              "method": "GET",
              "error": "net::ERR_ABORTED"
            },
            {
              "url": "https://www.scapestack.org/next?_rsc=5CB68i4pnAekjehf",
              "method": "GET",
              "error": "net::ERR_ABORTED"
            },
            {
              "url": "https://www.scapestack.org/dps?_rsc=7h4NYy5eoyMcNlUN",
              "method": "GET",
              "error": "net::ERR_ABORTED"
            }
          ],
          "horizontalOverflowPx": 0,
          "brokenImages": [],
          "unnamedControls": [],
          "headings": [
            {
              "level": "h1",
              "text": "Stop bankstanding.Pick the next trip."
            }
          ],
          "axHeadings": [
            "Stop bankstanding. Pick the next trip."
          ],
          "navigationTiming": {
            "responseStartMs": 89,
            "domContentLoadedMs": 196,
            "loadEventMs": 459
          }
        },
        {
          "mode": "warm",
          "status": 200,
          "shellReady": true,
          "shellReadyMs": 140,
          "ready": true,
          "navigationError": null,
          "readyError": null,
          "domContentLoadedMs": 110,
          "actionableMs": 140,
          "consoleErrors": [],
          "pageErrors": [],
          "hydrationErrors": [],
          "requestFailures": [
            {
              "url": "https://www.scapestack.org/next?_rsc=tXyZJ52UQVBCVsD3",
              "method": "GET",
              "error": "net::ERR_ABORTED"
            },
            {
              "url": "https://www.scapestack.org/bank?_rsc=7h4NYy5eoyMcNlUN",
              "method": "GET",
              "error": "net::ERR_ABORTED"
            },
            {
              "url": "https://www.scapestack.org/bank?_rsc=uaK0MgyDJoHiW1hD",
              "method": "GET",
              "error": "net::ERR_ABORTED"
            },
            {
              "url": "https://www.scapestack.org/?_rsc=8nTjltbQWvg6NcbE",
              "method": "GET",
              "error": "net::ERR_ABORTED"
            },
            {
              "url": "https://www.scapestack.org/bank?_rsc=B0XTjNdT1YmnFybB",
              "method": "GET",
              "error": "net::ERR_ABORTED"
            },
            {
              "url": "https://www.scapestack.org/_next/static/chunks/23azzoqgxnv38.js?dpl=dpl_B4Sc9oN7DAdLg9v6BdzJuK5EW8LC",
              "method": "GET",
              "error": "net::ERR_ABORTED"
            },
            {
              "url": "https://www.scapestack.org/_next/static/chunks/2357h3_hatpnc.js?dpl=dpl_B4Sc9oN7DAdLg9v6BdzJuK5EW8LC",
              "method": "GET",
              "error": "net::ERR_ABORTED"
            },
            {
              "url": "https://www.scapestack.org/next?_rsc=5CB68i4pnAekjehf",
              "method": "GET",
              "error": "net::ERR_ABORTED"
            }
          ],
          "horizontalOverflowPx": 0,
          "brokenImages": [],
          "unnamedControls": [],
          "headings": [
            {
              "level": "h1",
              "text": "Stop bankstanding.Pick the next trip."
            }
          ],
          "axHeadings": [
            "Stop bankstanding. Pick the next trip."
          ],
          "navigationTiming": {
            "responseStartMs": 94,
            "domContentLoadedMs": 108,
            "loadEventMs": 149
          }
        },
        {
          "mode": "warm",
          "status": 200,
          "shellReady": true,
          "shellReadyMs": 99,
          "ready": true,
          "navigationError": null,
          "readyError": null,
          "domContentLoadedMs": 71,
          "actionableMs": 99,
          "consoleErrors": [],
          "pageErrors": [],
          "hydrationErrors": [],
          "requestFailures": [
            {
              "url": "https://www.scapestack.org/next?_rsc=tXyZJ52UQVBCVsD3",
              "method": "GET",
              "error": "net::ERR_ABORTED"
            },
            {
              "url": "https://www.scapestack.org/next?_rsc=tXyZJ52UQVBCVsD3",
              "method": "GET",
              "error": "net::ERR_ABORTED"
            }
          ],
          "horizontalOverflowPx": 0,
          "brokenImages": [],
          "unnamedControls": [],
          "headings": [
            {
              "level": "h1",
              "text": "Stop bankstanding.Pick the next trip."
            }
          ],
          "axHeadings": [
            "Stop bankstanding. Pick the next trip."
          ],
          "navigationTiming": {
            "responseStartMs": 44,
            "domContentLoadedMs": 68,
            "loadEventMs": 118
          }
        }
      ],
      "summary": {
        "coldMedianMs": 819,
        "coldMinMs": 297,
        "coldMaxMs": 1261,
        "warmMedianMs": 140,
        "warmMinMs": 99,
        "warmMaxMs": 225,
        "readyRuns": 6,
        "errorCount": 0,
        "hydrationErrorCount": 0,
        "overflowRuns": 0,
        "brokenImageCount": 0,
        "unnamedControlCount": 0
      }
    },
    {
      "route": "next",
      "path": "/next?rsn=Lauky&intent=short&time=15",
      "viewport": {
        "id": "desktop",
        "width": 1440,
        "height": 1000,
        "isMobile": false
      },
      "cold": [
        {
          "mode": "cold",
          "status": 200,
          "shellReady": true,
          "shellReadyMs": 2902,
          "ready": true,
          "navigationError": null,
          "readyError": null,
          "domContentLoadedMs": 582,
          "actionableMs": 2902,
          "consoleErrors": [],
          "pageErrors": [],
          "hydrationErrors": [],
          "requestFailures": [
            {
              "url": "https://www.scapestack.org/next?rsn=Lauky&intent=short&time=15",
              "method": "POST",
              "error": "net::ERR_ABORTED"
            },
            {
              "url": "https://www.scapestack.org/next?rsn=Lauky&intent=short&time=15",
              "method": "POST",
              "error": "net::ERR_ABORTED"
            },
            {
              "url": "https://www.scapestack.org/quests/fairytale-ii-cure-a-queen?rsn=Lauky&from=next&bank=none&_rsc=oseKngdmXkzMHm7Q",
              "method": "GET",
              "error": "net::ERR_ABORTED"
            }
          ],
          "horizontalOverflowPx": 0,
          "brokenImages": [],
          "unnamedControls": [],
          "headings": [
            {
              "level": "h2",
              "text": "Unlock fairy rings"
            },
            {
              "level": "h3",
              "text": "Choose a different vibe"
            },
            {
              "level": "h2",
              "text": "More unlock moves"
            },
            {
              "level": "h3",
              "text": "Finish Western banner 4"
            },
            {
              "level": "h3",
              "text": "Collect 4 items for Druidic Ritual"
            },
            {
              "level": "h3",
              "text": "Collect 1 item for Tree Gnome Village"
            },
            {
              "level": "h3",
              "text": "Train Slayer to 95 for Kourend & Kebos Elite diary"
            },
            {
              "level": "h3",
              "text": "Train Runecraft to 78 for Varrock Elite diary"
            },
            {
              "level": "h2",
              "text": "Unlock gaps"
            },
            {
              "level": "h3",
              "text": "Barrows gloves route"
            },
            {
              "level": "h3",
              "text": "Fairy rings route"
            },
            {
              "level": "h3",
              "text": "Piety route"
            },
            {
              "level": "h3",
              "text": "Ava's assembler route"
            },
            {
              "level": "h3",
              "text": "Dragon defender route"
            },
            {
              "level": "h3",
              "text": "Quest cape route"
            },
            {
              "level": "h3",
              "text": "Raids prep route"
            },
            {
              "level": "h3",
              "text": "Slayer unlock route"
            },
            {
              "level": "h3",
              "text": "Routes to inspect"
            },
            {
              "level": "h3",
              "text": "Almost there"
            }
          ],
          "axHeadings": [
            "Unlock fairy rings",
            "Choose a different vibe",
            "Run herbs + birdhouses"
          ],
          "navigationTiming": {
            "responseStartMs": 133,
            "domContentLoadedMs": 574,
            "loadEventMs": 819
          },
          "axArtifact": "docs/qa/outcome-recovery/ODR-01/production/ax/desktop-next.json",
          "screenshotArtifact": "docs/qa/outcome-recovery/ODR-01/production/screenshots/desktop-next.png"
        },
        {
          "mode": "cold",
          "status": 200,
          "shellReady": true,
          "shellReadyMs": 3064,
          "ready": true,
          "navigationError": null,
          "readyError": null,
          "domContentLoadedMs": 1210,
          "actionableMs": 3064,
          "consoleErrors": [],
          "pageErrors": [],
          "hydrationErrors": [],
          "requestFailures": [
            {
              "url": "https://www.scapestack.org/next?rsn=Lauky&from=next&_rsc=oseKngdmXkzMHm7Q",
              "method": "GET",
              "error": "net::ERR_ABORTED"
            },
            {
              "url": "https://www.scapestack.org/next?rsn=Lauky&intent=short&time=15",
              "method": "POST",
              "error": "net::ERR_ABORTED"
            }
          ],
          "horizontalOverflowPx": 0,
          "brokenImages": [],
          "unnamedControls": [],
          "headings": [
            {
              "level": "h2",
              "text": "Run herbs + birdhouses"
            },
            {
              "level": "h2",
              "text": "More unlock moves"
            },
            {
              "level": "h3",
              "text": "Train Slayer to 95 for Kourend & Kebos Elite diary"
            },
            {
              "level": "h3",
              "text": "Train Runecraft to 78 for Varrock Elite diary"
            },
            {
              "level": "h3",
              "text": "Train Fletching to 95 for Desert Elite diary"
            },
            {
              "level": "h3",
              "text": "Train Sailing to 65 for The Graveyard"
            },
            {
              "level": "h3",
              "text": "Train Agility to 90 for Ardougne Elite diary"
            },
            {
              "level": "h2",
              "text": "Unlock gaps"
            },
            {
              "level": "h3",
              "text": "Barrows gloves route"
            },
            {
              "level": "h3",
              "text": "Fairy rings route"
            },
            {
              "level": "h3",
              "text": "Piety route"
            },
            {
              "level": "h3",
              "text": "Ava's assembler route"
            },
            {
              "level": "h3",
              "text": "Dragon defender route"
            },
            {
              "level": "h3",
              "text": "Quest cape route"
            },
            {
              "level": "h3",
              "text": "Raids prep route"
            },
            {
              "level": "h3",
              "text": "Slayer unlock route"
            },
            {
              "level": "h3",
              "text": "Routes to inspect"
            },
            {
              "level": "h3",
              "text": "Almost there"
            }
          ],
          "axHeadings": [
            "Run herbs + birdhouses"
          ],
          "navigationTiming": {
            "responseStartMs": 133,
            "domContentLoadedMs": 1210,
            "loadEventMs": 1461
          }
        },
        {
          "mode": "cold",
          "status": 200,
          "shellReady": true,
          "shellReadyMs": 2230,
          "ready": true,
          "navigationError": null,
          "readyError": null,
          "domContentLoadedMs": 900,
          "actionableMs": 2230,
          "consoleErrors": [],
          "pageErrors": [],
          "hydrationErrors": [],
          "requestFailures": [
            {
              "url": "https://www.scapestack.org/next?rsn=Lauky&intent=short&time=15",
              "method": "POST",
              "error": "net::ERR_ABORTED"
            }
          ],
          "horizontalOverflowPx": 0,
          "brokenImages": [],
          "unnamedControls": [],
          "headings": [
            {
              "level": "h2",
              "text": "Run herbs + birdhouses"
            },
            {
              "level": "h2",
              "text": "More unlock moves"
            },
            {
              "level": "h3",
              "text": "Train Slayer to 95 for Kourend & Kebos Elite diary"
            },
            {
              "level": "h3",
              "text": "Train Runecraft to 78 for Varrock Elite diary"
            },
            {
              "level": "h3",
              "text": "Train Fletching to 95 for Desert Elite diary"
            },
            {
              "level": "h3",
              "text": "Train Sailing to 65 for The Graveyard"
            },
            {
              "level": "h3",
              "text": "Train Agility to 90 for Ardougne Elite diary"
            },
            {
              "level": "h2",
              "text": "Unlock gaps"
            },
            {
              "level": "h3",
              "text": "Barrows gloves route"
            },
            {
              "level": "h3",
              "text": "Fairy rings route"
            },
            {
              "level": "h3",
              "text": "Piety route"
            },
            {
              "level": "h3",
              "text": "Ava's assembler route"
            },
            {
              "level": "h3",
              "text": "Dragon defender route"
            },
            {
              "level": "h3",
              "text": "Quest cape route"
            },
            {
              "level": "h3",
              "text": "Raids prep route"
            },
            {
              "level": "h3",
              "text": "Slayer unlock route"
            },
            {
              "level": "h3",
              "text": "Routes to inspect"
            },
            {
              "level": "h3",
              "text": "Almost there"
            }
          ],
          "axHeadings": [
            "Run herbs + birdhouses"
          ],
          "navigationTiming": {
            "responseStartMs": 434,
            "domContentLoadedMs": 899,
            "loadEventMs": 921
          }
        }
      ],
      "warm": [
        {
          "mode": "warm",
          "status": 200,
          "shellReady": true,
          "shellReadyMs": 1697,
          "ready": true,
          "navigationError": null,
          "readyError": null,
          "domContentLoadedMs": 385,
          "actionableMs": 1697,
          "consoleErrors": [],
          "pageErrors": [],
          "hydrationErrors": [],
          "requestFailures": [
            {
              "url": "https://www.scapestack.org/next?rsn=Lauky&from=next&_rsc=oseKngdmXkzMHm7Q",
              "method": "GET",
              "error": "net::ERR_ABORTED"
            },
            {
              "url": "https://www.scapestack.org/next?rsn=Lauky&intent=short&time=15",
              "method": "POST",
              "error": "net::ERR_ABORTED"
            },
            {
              "url": "https://www.scapestack.org/next?rsn=Lauky&intent=short&time=15",
              "method": "POST",
              "error": "net::ERR_ABORTED"
            }
          ],
          "horizontalOverflowPx": 0,
          "brokenImages": [],
          "unnamedControls": [],
          "headings": [
            {
              "level": "h2",
              "text": "Run herbs + birdhouses"
            },
            {
              "level": "h2",
              "text": "More unlock moves"
            },
            {
              "level": "h3",
              "text": "Train Slayer to 95 for Kourend & Kebos Elite diary"
            },
            {
              "level": "h3",
              "text": "Train Runecraft to 78 for Varrock Elite diary"
            },
            {
              "level": "h3",
              "text": "Train Fletching to 95 for Desert Elite diary"
            },
            {
              "level": "h3",
              "text": "Train Sailing to 65 for The Graveyard"
            },
            {
              "level": "h3",
              "text": "Train Agility to 90 for Ardougne Elite diary"
            },
            {
              "level": "h2",
              "text": "Unlock gaps"
            },
            {
              "level": "h3",
              "text": "Barrows gloves route"
            },
            {
              "level": "h3",
              "text": "Fairy rings route"
            },
            {
              "level": "h3",
              "text": "Piety route"
            },
            {
              "level": "h3",
              "text": "Ava's assembler route"
            },
            {
              "level": "h3",
              "text": "Dragon defender route"
            },
            {
              "level": "h3",
              "text": "Quest cape route"
            },
            {
              "level": "h3",
              "text": "Raids prep route"
            },
            {
              "level": "h3",
              "text": "Slayer unlock route"
            },
            {
              "level": "h3",
              "text": "Routes to inspect"
            },
            {
              "level": "h3",
              "text": "Almost there"
            }
          ],
          "axHeadings": [
            "Run herbs + birdhouses"
          ],
          "navigationTiming": {
            "responseStartMs": 45,
            "domContentLoadedMs": 383,
            "loadEventMs": 384
          }
        },
        {
          "mode": "warm",
          "status": 200,
          "shellReady": true,
          "shellReadyMs": 1708,
          "ready": true,
          "navigationError": null,
          "readyError": null,
          "domContentLoadedMs": 403,
          "actionableMs": 1708,
          "consoleErrors": [],
          "pageErrors": [],
          "hydrationErrors": [],
          "requestFailures": [
            {
              "url": "https://www.scapestack.org/next?rsn=Lauky&from=next&_rsc=oseKngdmXkzMHm7Q",
              "method": "GET",
              "error": "net::ERR_ABORTED"
            }
          ],
          "horizontalOverflowPx": 0,
          "brokenImages": [],
          "unnamedControls": [],
          "headings": [
            {
              "level": "h2",
              "text": "Run herbs + birdhouses"
            },
            {
              "level": "h2",
              "text": "More unlock moves"
            },
            {
              "level": "h3",
              "text": "Train Slayer to 95 for Kourend & Kebos Elite diary"
            },
            {
              "level": "h3",
              "text": "Train Runecraft to 78 for Varrock Elite diary"
            },
            {
              "level": "h3",
              "text": "Train Fletching to 95 for Desert Elite diary"
            },
            {
              "level": "h3",
              "text": "Train Sailing to 65 for The Graveyard"
            },
            {
              "level": "h3",
              "text": "Train Agility to 90 for Ardougne Elite diary"
            },
            {
              "level": "h2",
              "text": "Unlock gaps"
            },
            {
              "level": "h3",
              "text": "Barrows gloves route"
            },
            {
              "level": "h3",
              "text": "Fairy rings route"
            },
            {
              "level": "h3",
              "text": "Piety route"
            },
            {
              "level": "h3",
              "text": "Ava's assembler route"
            },
            {
              "level": "h3",
              "text": "Dragon defender route"
            },
            {
              "level": "h3",
              "text": "Quest cape route"
            },
            {
              "level": "h3",
              "text": "Raids prep route"
            },
            {
              "level": "h3",
              "text": "Slayer unlock route"
            },
            {
              "level": "h3",
              "text": "Routes to inspect"
            },
            {
              "level": "h3",
              "text": "Almost there"
            }
          ],
          "axHeadings": [
            "Run herbs + birdhouses"
          ],
          "navigationTiming": {
            "responseStartMs": 75,
            "domContentLoadedMs": 401,
            "loadEventMs": 402
          }
        },
        {
          "mode": "warm",
          "status": 200,
          "shellReady": true,
          "shellReadyMs": 1783,
          "ready": true,
          "navigationError": null,
          "readyError": null,
          "domContentLoadedMs": 457,
          "actionableMs": 1783,
          "consoleErrors": [],
          "pageErrors": [],
          "hydrationErrors": [],
          "requestFailures": [
            {
              "url": "https://www.scapestack.org/next?rsn=Lauky&intent=short&time=15",
              "method": "POST",
              "error": "net::ERR_ABORTED"
            }
          ],
          "horizontalOverflowPx": 0,
          "brokenImages": [],
          "unnamedControls": [],
          "headings": [
            {
              "level": "h2",
              "text": "Run herbs + birdhouses"
            },
            {
              "level": "h2",
              "text": "More unlock moves"
            },
            {
              "level": "h3",
              "text": "Train Slayer to 95 for Kourend & Kebos Elite diary"
            },
            {
              "level": "h3",
              "text": "Train Runecraft to 78 for Varrock Elite diary"
            },
            {
              "level": "h3",
              "text": "Train Fletching to 95 for Desert Elite diary"
            },
            {
              "level": "h3",
              "text": "Train Sailing to 65 for The Graveyard"
            },
            {
              "level": "h3",
              "text": "Train Agility to 90 for Ardougne Elite diary"
            },
            {
              "level": "h2",
              "text": "Unlock gaps"
            },
            {
              "level": "h3",
              "text": "Barrows gloves route"
            },
            {
              "level": "h3",
              "text": "Fairy rings route"
            },
            {
              "level": "h3",
              "text": "Piety route"
            },
            {
              "level": "h3",
              "text": "Ava's assembler route"
            },
            {
              "level": "h3",
              "text": "Dragon defender route"
            },
            {
              "level": "h3",
              "text": "Quest cape route"
            },
            {
              "level": "h3",
              "text": "Raids prep route"
            },
            {
              "level": "h3",
              "text": "Slayer unlock route"
            },
            {
              "level": "h3",
              "text": "Routes to inspect"
            },
            {
              "level": "h3",
              "text": "Almost there"
            }
          ],
          "axHeadings": [
            "Run herbs + birdhouses"
          ],
          "navigationTiming": {
            "responseStartMs": 407,
            "domContentLoadedMs": 454,
            "loadEventMs": 483
          }
        }
      ],
      "summary": {
        "coldMedianMs": 2902,
        "coldMinMs": 2230,
        "coldMaxMs": 3064,
        "warmMedianMs": 1708,
        "warmMinMs": 1697,
        "warmMaxMs": 1783,
        "readyRuns": 6,
        "errorCount": 0,
        "hydrationErrorCount": 0,
        "overflowRuns": 0,
        "brokenImageCount": 0,
        "unnamedControlCount": 0
      }
    },
    {
      "route": "home",
      "path": "/",
      "viewport": {
        "id": "mobile",
        "width": 390,
        "height": 844,
        "isMobile": true
      },
      "cold": [
        {
          "mode": "cold",
          "status": 200,
          "shellReady": true,
          "shellReadyMs": 304,
          "ready": true,
          "navigationError": null,
          "readyError": null,
          "domContentLoadedMs": 288,
          "actionableMs": 304,
          "consoleErrors": [],
          "pageErrors": [],
          "hydrationErrors": [],
          "requestFailures": [],
          "horizontalOverflowPx": 0,
          "brokenImages": [],
          "unnamedControls": [],
          "headings": [
            {
              "level": "h1",
              "text": "Stop bankstanding.Pick the next trip."
            }
          ],
          "axHeadings": [
            "Stop bankstanding. Pick the next trip."
          ],
          "navigationTiming": {
            "responseStartMs": 203,
            "domContentLoadedMs": 288,
            "loadEventMs": 403
          },
          "axArtifact": "docs/qa/outcome-recovery/ODR-01/production/ax/mobile-home.json",
          "screenshotArtifact": "docs/qa/outcome-recovery/ODR-01/production/screenshots/mobile-home.png"
        },
        {
          "mode": "cold",
          "status": 200,
          "shellReady": true,
          "shellReadyMs": 255,
          "ready": true,
          "navigationError": null,
          "readyError": null,
          "domContentLoadedMs": 242,
          "actionableMs": 255,
          "consoleErrors": [],
          "pageErrors": [],
          "hydrationErrors": [],
          "requestFailures": [],
          "horizontalOverflowPx": 0,
          "brokenImages": [],
          "unnamedControls": [],
          "headings": [
            {
              "level": "h1",
              "text": "Stop bankstanding.Pick the next trip."
            }
          ],
          "axHeadings": [
            "Stop bankstanding. Pick the next trip."
          ],
          "navigationTiming": {
            "responseStartMs": 133,
            "domContentLoadedMs": 241,
            "loadEventMs": 414
          }
        },
        {
          "mode": "cold",
          "status": 200,
          "shellReady": true,
          "shellReadyMs": 421,
          "ready": true,
          "navigationError": null,
          "readyError": null,
          "domContentLoadedMs": 398,
          "actionableMs": 421,
          "consoleErrors": [],
          "pageErrors": [],
          "hydrationErrors": [],
          "requestFailures": [],
          "horizontalOverflowPx": 0,
          "brokenImages": [],
          "unnamedControls": [],
          "headings": [
            {
              "level": "h1",
              "text": "Stop bankstanding.Pick the next trip."
            }
          ],
          "axHeadings": [
            "Stop bankstanding. Pick the next trip."
          ],
          "navigationTiming": {
            "responseStartMs": 135,
            "domContentLoadedMs": 397,
            "loadEventMs": 397
          }
        }
      ],
      "warm": [
        {
          "mode": "warm",
          "status": 200,
          "shellReady": true,
          "shellReadyMs": 86,
          "ready": true,
          "navigationError": null,
          "readyError": null,
          "domContentLoadedMs": 63,
          "actionableMs": 86,
          "consoleErrors": [],
          "pageErrors": [],
          "hydrationErrors": [],
          "requestFailures": [],
          "horizontalOverflowPx": 0,
          "brokenImages": [],
          "unnamedControls": [],
          "headings": [
            {
              "level": "h1",
              "text": "Stop bankstanding.Pick the next trip."
            }
          ],
          "axHeadings": [
            "Stop bankstanding. Pick the next trip."
          ],
          "navigationTiming": {
            "responseStartMs": 42,
            "domContentLoadedMs": 63,
            "loadEventMs": 137
          }
        },
        {
          "mode": "warm",
          "status": 200,
          "shellReady": true,
          "shellReadyMs": 76,
          "ready": true,
          "navigationError": null,
          "readyError": null,
          "domContentLoadedMs": 54,
          "actionableMs": 76,
          "consoleErrors": [],
          "pageErrors": [],
          "hydrationErrors": [],
          "requestFailures": [],
          "horizontalOverflowPx": 0,
          "brokenImages": [],
          "unnamedControls": [],
          "headings": [
            {
              "level": "h1",
              "text": "Stop bankstanding.Pick the next trip."
            }
          ],
          "axHeadings": [
            "Stop bankstanding. Pick the next trip."
          ],
          "navigationTiming": {
            "responseStartMs": 40,
            "domContentLoadedMs": 53,
            "loadEventMs": 98
          }
        },
        {
          "mode": "warm",
          "status": 200,
          "shellReady": true,
          "shellReadyMs": 134,
          "ready": true,
          "navigationError": null,
          "readyError": null,
          "domContentLoadedMs": 110,
          "actionableMs": 134,
          "consoleErrors": [],
          "pageErrors": [],
          "hydrationErrors": [],
          "requestFailures": [],
          "horizontalOverflowPx": 0,
          "brokenImages": [],
          "unnamedControls": [],
          "headings": [
            {
              "level": "h1",
              "text": "Stop bankstanding.Pick the next trip."
            }
          ],
          "axHeadings": [
            "Stop bankstanding. Pick the next trip."
          ],
          "navigationTiming": {
            "responseStartMs": 95,
            "domContentLoadedMs": 110,
            "loadEventMs": 155
          }
        }
      ],
      "summary": {
        "coldMedianMs": 304,
        "coldMinMs": 255,
        "coldMaxMs": 421,
        "warmMedianMs": 86,
        "warmMinMs": 76,
        "warmMaxMs": 134,
        "readyRuns": 6,
        "errorCount": 0,
        "hydrationErrorCount": 0,
        "overflowRuns": 0,
        "brokenImageCount": 0,
        "unnamedControlCount": 0
      }
    },
    {
      "route": "next",
      "path": "/next?rsn=Lauky&intent=short&time=15",
      "viewport": {
        "id": "mobile",
        "width": 390,
        "height": 844,
        "isMobile": true
      },
      "cold": [
        {
          "mode": "cold",
          "status": 200,
          "shellReady": true,
          "shellReadyMs": 1744,
          "ready": true,
          "navigationError": null,
          "readyError": null,
          "domContentLoadedMs": 423,
          "actionableMs": 1744,
          "consoleErrors": [],
          "pageErrors": [],
          "hydrationErrors": [],
          "requestFailures": [
            {
              "url": "https://www.scapestack.org/next?rsn=Lauky&_rsc=1xvxz12uuu4-K_Rk",
              "method": "GET",
              "error": "net::ERR_ABORTED"
            },
            {
              "url": "https://www.scapestack.org/next?rsn=Lauky&intent=short&time=15",
              "method": "POST",
              "error": "net::ERR_ABORTED"
            }
          ],
          "horizontalOverflowPx": 0,
          "brokenImages": [],
          "unnamedControls": [],
          "headings": [
            {
              "level": "h2",
              "text": "Run herbs + birdhouses"
            },
            {
              "level": "h2",
              "text": "More unlock moves"
            },
            {
              "level": "h3",
              "text": "Train Slayer to 95 for Kourend & Kebos Elite diary"
            },
            {
              "level": "h3",
              "text": "Train Runecraft to 78 for Varrock Elite diary"
            },
            {
              "level": "h3",
              "text": "Train Fletching to 95 for Desert Elite diary"
            },
            {
              "level": "h3",
              "text": "Train Sailing to 65 for The Graveyard"
            },
            {
              "level": "h3",
              "text": "Train Agility to 90 for Ardougne Elite diary"
            },
            {
              "level": "h2",
              "text": "Unlock gaps"
            },
            {
              "level": "h3",
              "text": "Barrows gloves route"
            },
            {
              "level": "h3",
              "text": "Fairy rings route"
            },
            {
              "level": "h3",
              "text": "Piety route"
            },
            {
              "level": "h3",
              "text": "Ava's assembler route"
            },
            {
              "level": "h3",
              "text": "Dragon defender route"
            },
            {
              "level": "h3",
              "text": "Quest cape route"
            },
            {
              "level": "h3",
              "text": "Raids prep route"
            },
            {
              "level": "h3",
              "text": "Slayer unlock route"
            },
            {
              "level": "h3",
              "text": "Routes to inspect"
            },
            {
              "level": "h3",
              "text": "Almost there"
            }
          ],
          "axHeadings": [
            "Run herbs + birdhouses"
          ],
          "navigationTiming": {
            "responseStartMs": 215,
            "domContentLoadedMs": 422,
            "loadEventMs": 540
          },
          "axArtifact": "docs/qa/outcome-recovery/ODR-01/production/ax/mobile-next.json",
          "screenshotArtifact": "docs/qa/outcome-recovery/ODR-01/production/screenshots/mobile-next.png"
        },
        {
          "mode": "cold",
          "status": 200,
          "shellReady": true,
          "shellReadyMs": 1653,
          "ready": true,
          "navigationError": null,
          "readyError": null,
          "domContentLoadedMs": 350,
          "actionableMs": 1653,
          "consoleErrors": [],
          "pageErrors": [],
          "hydrationErrors": [],
          "requestFailures": [
            {
              "url": "https://www.scapestack.org/next?_rsc=oseKngdmXkzMHm7Q",
              "method": "GET",
              "error": "net::ERR_ABORTED"
            },
            {
              "url": "https://www.scapestack.org/next?rsn=Lauky&intent=short&time=15",
              "method": "POST",
              "error": "net::ERR_ABORTED"
            },
            {
              "url": "https://www.scapestack.org/next?rsn=Lauky&_rsc=1xvxz12uuu4-K_Rk",
              "method": "GET",
              "error": "net::ERR_ABORTED"
            },
            {
              "url": "https://www.scapestack.org/next?rsn=Lauky&intent=short&time=15",
              "method": "POST",
              "error": "net::ERR_ABORTED"
            },
            {
              "url": "https://www.scapestack.org/next?rsn=Lauky&intent=short&time=15&_rsc=oseKngdmXkzMHm7Q",
              "method": "GET",
              "error": "net::ERR_ABORTED"
            }
          ],
          "horizontalOverflowPx": 0,
          "brokenImages": [],
          "unnamedControls": [],
          "headings": [
            {
              "level": "h2",
              "text": "Run herbs + birdhouses"
            },
            {
              "level": "h2",
              "text": "More unlock moves"
            },
            {
              "level": "h3",
              "text": "Train Slayer to 95 for Kourend & Kebos Elite diary"
            },
            {
              "level": "h3",
              "text": "Train Runecraft to 78 for Varrock Elite diary"
            },
            {
              "level": "h3",
              "text": "Train Fletching to 95 for Desert Elite diary"
            },
            {
              "level": "h3",
              "text": "Train Sailing to 65 for The Graveyard"
            },
            {
              "level": "h3",
              "text": "Train Agility to 90 for Ardougne Elite diary"
            },
            {
              "level": "h2",
              "text": "Unlock gaps"
            },
            {
              "level": "h3",
              "text": "Barrows gloves route"
            },
            {
              "level": "h3",
              "text": "Fairy rings route"
            },
            {
              "level": "h3",
              "text": "Piety route"
            },
            {
              "level": "h3",
              "text": "Ava's assembler route"
            },
            {
              "level": "h3",
              "text": "Dragon defender route"
            },
            {
              "level": "h3",
              "text": "Quest cape route"
            },
            {
              "level": "h3",
              "text": "Raids prep route"
            },
            {
              "level": "h3",
              "text": "Slayer unlock route"
            },
            {
              "level": "h3",
              "text": "Routes to inspect"
            },
            {
              "level": "h3",
              "text": "Almost there"
            }
          ],
          "axHeadings": [
            "Run herbs + birdhouses"
          ],
          "navigationTiming": {
            "responseStartMs": 202,
            "domContentLoadedMs": 349,
            "loadEventMs": 467
          }
        },
        {
          "mode": "cold",
          "status": 200,
          "shellReady": true,
          "shellReadyMs": 1154,
          "ready": true,
          "navigationError": null,
          "readyError": null,
          "domContentLoadedMs": 343,
          "actionableMs": 1154,
          "consoleErrors": [],
          "pageErrors": [],
          "hydrationErrors": [],
          "requestFailures": [
            {
              "url": "https://www.scapestack.org/next?rsn=Lauky&_rsc=1xvxz12uuu4-K_Rk",
              "method": "GET",
              "error": "net::ERR_ABORTED"
            },
            {
              "url": "https://www.scapestack.org/next?rsn=Lauky&intent=short&time=15",
              "method": "POST",
              "error": "net::ERR_ABORTED"
            },
            {
              "url": "https://www.scapestack.org/next?rsn=Lauky&intent=short&time=15&_rsc=oseKngdmXkzMHm7Q",
              "method": "GET",
              "error": "net::ERR_ABORTED"
            }
          ],
          "horizontalOverflowPx": 0,
          "brokenImages": [],
          "unnamedControls": [],
          "headings": [
            {
              "level": "h2",
              "text": "Run herbs + birdhouses"
            },
            {
              "level": "h2",
              "text": "More unlock moves"
            },
            {
              "level": "h3",
              "text": "Train Slayer to 95 for Kourend & Kebos Elite diary"
            },
            {
              "level": "h3",
              "text": "Train Runecraft to 78 for Varrock Elite diary"
            },
            {
              "level": "h3",
              "text": "Train Fletching to 95 for Desert Elite diary"
            },
            {
              "level": "h3",
              "text": "Train Sailing to 65 for The Graveyard"
            },
            {
              "level": "h3",
              "text": "Train Agility to 90 for Ardougne Elite diary"
            },
            {
              "level": "h2",
              "text": "Unlock gaps"
            },
            {
              "level": "h3",
              "text": "Barrows gloves route"
            },
            {
              "level": "h3",
              "text": "Fairy rings route"
            },
            {
              "level": "h3",
              "text": "Piety route"
            },
            {
              "level": "h3",
              "text": "Ava's assembler route"
            },
            {
              "level": "h3",
              "text": "Dragon defender route"
            },
            {
              "level": "h3",
              "text": "Quest cape route"
            },
            {
              "level": "h3",
              "text": "Raids prep route"
            },
            {
              "level": "h3",
              "text": "Slayer unlock route"
            },
            {
              "level": "h3",
              "text": "Routes to inspect"
            },
            {
              "level": "h3",
              "text": "Almost there"
            }
          ],
          "axHeadings": [
            "Run herbs + birdhouses"
          ],
          "navigationTiming": {
            "responseStartMs": 140,
            "domContentLoadedMs": 342,
            "loadEventMs": 456
          }
        }
      ],
      "warm": [
        {
          "mode": "warm",
          "status": 200,
          "shellReady": true,
          "shellReadyMs": 1050,
          "ready": true,
          "navigationError": null,
          "readyError": null,
          "domContentLoadedMs": 245,
          "actionableMs": 1050,
          "consoleErrors": [],
          "pageErrors": [],
          "hydrationErrors": [],
          "requestFailures": [
            {
              "url": "https://www.scapestack.org/next?rsn=Lauky&intent=short&time=15&_rsc=oseKngdmXkzMHm7Q",
              "method": "GET",
              "error": "net::ERR_ABORTED"
            },
            {
              "url": "https://www.scapestack.org/next?rsn=Lauky&intent=short&time=15",
              "method": "POST",
              "error": "net::ERR_ABORTED"
            }
          ],
          "horizontalOverflowPx": 0,
          "brokenImages": [],
          "unnamedControls": [],
          "headings": [
            {
              "level": "h2",
              "text": "Run herbs + birdhouses"
            },
            {
              "level": "h2",
              "text": "More unlock moves"
            },
            {
              "level": "h3",
              "text": "Train Slayer to 95 for Kourend & Kebos Elite diary"
            },
            {
              "level": "h3",
              "text": "Train Runecraft to 78 for Varrock Elite diary"
            },
            {
              "level": "h3",
              "text": "Train Fletching to 95 for Desert Elite diary"
            },
            {
              "level": "h3",
              "text": "Train Sailing to 65 for The Graveyard"
            },
            {
              "level": "h3",
              "text": "Train Agility to 90 for Ardougne Elite diary"
            },
            {
              "level": "h2",
              "text": "Unlock gaps"
            },
            {
              "level": "h3",
              "text": "Barrows gloves route"
            },
            {
              "level": "h3",
              "text": "Fairy rings route"
            },
            {
              "level": "h3",
              "text": "Piety route"
            },
            {
              "level": "h3",
              "text": "Ava's assembler route"
            },
            {
              "level": "h3",
              "text": "Dragon defender route"
            },
            {
              "level": "h3",
              "text": "Quest cape route"
            },
            {
              "level": "h3",
              "text": "Raids prep route"
            },
            {
              "level": "h3",
              "text": "Slayer unlock route"
            },
            {
              "level": "h3",
              "text": "Routes to inspect"
            },
            {
              "level": "h3",
              "text": "Almost there"
            }
          ],
          "axHeadings": [
            "Run herbs + birdhouses"
          ],
          "navigationTiming": {
            "responseStartMs": 88,
            "domContentLoadedMs": 244,
            "loadEventMs": 244
          }
        },
        {
          "mode": "warm",
          "status": 200,
          "shellReady": true,
          "shellReadyMs": 992,
          "ready": true,
          "navigationError": null,
          "readyError": null,
          "domContentLoadedMs": 176,
          "actionableMs": 992,
          "consoleErrors": [],
          "pageErrors": [],
          "hydrationErrors": [],
          "requestFailures": [
            {
              "url": "https://www.scapestack.org/next?rsn=Lauky&intent=short&time=15&_rsc=oseKngdmXkzMHm7Q",
              "method": "GET",
              "error": "net::ERR_ABORTED"
            },
            {
              "url": "https://www.scapestack.org/next?rsn=Lauky&intent=short&time=15",
              "method": "POST",
              "error": "net::ERR_ABORTED"
            },
            {
              "url": "https://www.scapestack.org/next?_rsc=1xvxz12uuu4-K_Rk",
              "method": "GET",
              "error": "net::ERR_ABORTED"
            },
            {
              "url": "https://www.scapestack.org/next?rsn=Lauky&intent=short&time=15",
              "method": "POST",
              "error": "net::ERR_ABORTED"
            }
          ],
          "horizontalOverflowPx": 0,
          "brokenImages": [],
          "unnamedControls": [],
          "headings": [
            {
              "level": "h2",
              "text": "Run herbs + birdhouses"
            },
            {
              "level": "h2",
              "text": "More unlock moves"
            },
            {
              "level": "h3",
              "text": "Train Slayer to 95 for Kourend & Kebos Elite diary"
            },
            {
              "level": "h3",
              "text": "Train Runecraft to 78 for Varrock Elite diary"
            },
            {
              "level": "h3",
              "text": "Train Fletching to 95 for Desert Elite diary"
            },
            {
              "level": "h3",
              "text": "Train Sailing to 65 for The Graveyard"
            },
            {
              "level": "h3",
              "text": "Train Agility to 90 for Ardougne Elite diary"
            },
            {
              "level": "h2",
              "text": "Unlock gaps"
            },
            {
              "level": "h3",
              "text": "Barrows gloves route"
            },
            {
              "level": "h3",
              "text": "Fairy rings route"
            },
            {
              "level": "h3",
              "text": "Piety route"
            },
            {
              "level": "h3",
              "text": "Ava's assembler route"
            },
            {
              "level": "h3",
              "text": "Dragon defender route"
            },
            {
              "level": "h3",
              "text": "Quest cape route"
            },
            {
              "level": "h3",
              "text": "Raids prep route"
            },
            {
              "level": "h3",
              "text": "Slayer unlock route"
            },
            {
              "level": "h3",
              "text": "Routes to inspect"
            },
            {
              "level": "h3",
              "text": "Almost there"
            }
          ],
          "axHeadings": [
            "Run herbs + birdhouses"
          ],
          "navigationTiming": {
            "responseStartMs": 43,
            "domContentLoadedMs": 174,
            "loadEventMs": 204
          }
        },
        {
          "mode": "warm",
          "status": 200,
          "shellReady": true,
          "shellReadyMs": 1005,
          "ready": true,
          "navigationError": null,
          "readyError": null,
          "domContentLoadedMs": 199,
          "actionableMs": 1005,
          "consoleErrors": [],
          "pageErrors": [],
          "hydrationErrors": [],
          "requestFailures": [
            {
              "url": "https://www.scapestack.org/next?_rsc=1xvxz12uuu4-K_Rk",
              "method": "GET",
              "error": "net::ERR_ABORTED"
            },
            {
              "url": "https://www.scapestack.org/next?rsn=Lauky&intent=short&time=15",
              "method": "POST",
              "error": "net::ERR_ABORTED"
            }
          ],
          "horizontalOverflowPx": 0,
          "brokenImages": [],
          "unnamedControls": [],
          "headings": [
            {
              "level": "h2",
              "text": "Run herbs + birdhouses"
            },
            {
              "level": "h2",
              "text": "More unlock moves"
            },
            {
              "level": "h3",
              "text": "Train Slayer to 95 for Kourend & Kebos Elite diary"
            },
            {
              "level": "h3",
              "text": "Train Runecraft to 78 for Varrock Elite diary"
            },
            {
              "level": "h3",
              "text": "Train Fletching to 95 for Desert Elite diary"
            },
            {
              "level": "h3",
              "text": "Train Sailing to 65 for The Graveyard"
            },
            {
              "level": "h3",
              "text": "Train Agility to 90 for Ardougne Elite diary"
            },
            {
              "level": "h2",
              "text": "Unlock gaps"
            },
            {
              "level": "h3",
              "text": "Barrows gloves route"
            },
            {
              "level": "h3",
              "text": "Fairy rings route"
            },
            {
              "level": "h3",
              "text": "Piety route"
            },
            {
              "level": "h3",
              "text": "Ava's assembler route"
            },
            {
              "level": "h3",
              "text": "Dragon defender route"
            },
            {
              "level": "h3",
              "text": "Quest cape route"
            },
            {
              "level": "h3",
              "text": "Raids prep route"
            },
            {
              "level": "h3",
              "text": "Slayer unlock route"
            },
            {
              "level": "h3",
              "text": "Routes to inspect"
            },
            {
              "level": "h3",
              "text": "Almost there"
            }
          ],
          "axHeadings": [
            "Run herbs + birdhouses"
          ],
          "navigationTiming": {
            "responseStartMs": 118,
            "domContentLoadedMs": 198,
            "loadEventMs": 198
          }
        }
      ],
      "summary": {
        "coldMedianMs": 1653,
        "coldMinMs": 1154,
        "coldMaxMs": 1744,
        "warmMedianMs": 1005,
        "warmMinMs": 992,
        "warmMaxMs": 1050,
        "readyRuns": 6,
        "errorCount": 0,
        "hydrationErrorCount": 0,
        "overflowRuns": 0,
        "brokenImageCount": 0,
        "unnamedControlCount": 0
      }
    }
  ],
  "summary": {
    "routeViewportPairs": 4,
    "measuredNavigations": 24,
    "failedReadyRuns": 0,
    "consoleErrors": 0,
    "pageErrors": 0,
    "hydrationErrors": 0,
    "overflowRuns": 0,
    "brokenImages": 0,
    "unnamedControls": 0
  }
}
